[ {"name": "Catch Blastoise, Feraligatr, or Swampert"},{"name": "Have a pokemon KO itself with Struggle"},{"name": "Visit Saffron Fighting Dojo"},{"name": "Defeat Misty "},{"name": "Obtain TM26 (Thunderbolt)"},{"name": "Obtain HM03 (Surf)"},{"name": "Have a pokemon with Clear Body or Cloud Nine"},{"name": "Catch Ludicolo or Shiftry"},{"name": "testicles"},{"name": "Have a pokemon with 1 HP remaining"},{"name": "Catch 10 different Normal type pokemon"},{"name": "Defeat your Rival twice "},{"name": "Defeat your Rival three times"},{"name": "Only purchase items in groups of 10"},{"name": "Catch Butterfree or Beedrill"},{"name": "Only captured pokemon of one gender"},{"name": "Obtain TM47 (Water Pulse)"},{"name": "Release 10 unique pokemon "},{"name": "Use a Fire Stone "},{"name": "Use a Moon Stone"},{"name": "Visit Mr. Fuji's House"},{"name": "Visit Victory Road"},{"name": "Have a pokemon with Battle Armor or Blaze"},{"name": "Defeat 5 Black Belts"},{"name": "Defeat 10 Hikers"} ]